codelock/__init__.py
codelock/cdcli.py
Codelock-2.1.1.dist-info/LICENSE.txt
Codelock-2.1.1.dist-info/METADATA
Codelock-2.1.1.dist-info/WHEEL
Codelock-2.1.1.dist-info/entry_points.txt
Codelock-2.1.1.dist-info/top_level.txt
Codelock-2.1.1.dist-info/RECORD
